{
  "vehicles":[
      {
        "year":"2011",
        "make":"Honda",
        "model":"Element",
        "trim":"LX",
        "price":"$6,995",
        "color":"Alabaster Silver Metallic",
        "miles":"259,794",
        "category":"SUV",
        "engine":"2.4 L 4-cylinder",
        "vin":"5J6Yh1h34BL001874",
        "features":[
          {

          }
        ],
        "thumbnail":"/images/cars/2011-element/2011-honda-element",
        "images":[
          "/images/cars/2011-element/2011-honda-element-front",
          "/images/cars/2011-element/2011-honda-element-back-side",
          "/images/cars/2011-element/2011-honda-element-rear"
          ]
      }
    ]
  }
